sws_api_client/__init__.py
sws_api_client/auth.py
sws_api_client/codelist.py
sws_api_client/data_retrieval.py
sws_api_client/datasets.py
sws_api_client/datatable.py
sws_api_client/db.py
sws_api_client/discover.py
sws_api_client/files.py
sws_api_client/flaglist.py
sws_api_client/generic_models.py
sws_api_client/mail.py
sws_api_client/metadata_instances.py
sws_api_client/plugins.py
sws_api_client/s3.py
sws_api_client/sessions.py
sws_api_client/sws_api_client.py
sws_api_client/tags.py
sws_api_client/tasks.py
sws_api_client/token.py
sws_api_client-2.7.3.dist-info/METADATA
sws_api_client-2.7.3.dist-info/WHEEL
sws_api_client-2.7.3.dist-info/licenses/LICENSE
sws_api_client-2.7.3.dist-info/RECORD
